anvil/__init__.py
anvil/_components.py
anvil/_serialise.py
anvil/_server.py
anvil/_threaded_server.py
anvil/alchemy.py
anvil/app_creator.py
anvil/email.py
anvil/history.py
anvil/js.py
anvil/media.py
anvil/mpl_util.py
anvil/pdf.py
anvil/regex.py
anvil/run_app_via_uplink.py
anvil/secrets.py
anvil/server.py
anvil/stripe.py
anvil/tz.py
anvil/util.py
anvil/ext_data/__init__.py
anvil/ext_data/impl/__init__.py
anvil/ext_data/impl/lazy_iter.py
anvil/ext_data/impl/backends/__init__.py
anvil/ext_data/impl/backends/sql.py
anvil/facebook/__init__.py
anvil/facebook/auth.py
anvil/files/__init__.py
anvil/google/__init__.py
anvil/google/auth.py
anvil/google/drive.py
anvil/google/mail.py
anvil/google/sheets.py
anvil/microsoft/__init__.py
anvil/microsoft/auth.py
anvil/plotly_templates/__init__.py
anvil/tables/__init__.py
anvil/tables/_base_classes.py
anvil/tables/_config.py
anvil/tables/_errors.py
anvil/tables/_helpers.py
anvil/tables/query.py
anvil/tables/v2/__init__.py
anvil/tables/v2/_app_tables.py
anvil/tables/v2/_batcher.py
anvil/tables/v2/_constants.py
anvil/tables/v2/_load_hacks.py
anvil/tables/v2/_model.py
anvil/tables/v2/_refs.py
anvil/tables/v2/_row.py
anvil/tables/v2/_search.py
anvil/tables/v2/_table.py
anvil/tables/v2/_utils.py
anvil/users/__init__.py
anvil/users/config.py
anvil/users/exceptions.py
anvil/users/google_button.py
anvil/users/mfa/__init__.py
facebook/__init__.py
facebook/auth.py
google/__init__.py
google/auth.py
google/drive.py
google/mail.py
google/sheets.py
tables/__init__.py
anvil_uplink-0.6.0.dist-info/METADATA
anvil_uplink-0.6.0.dist-info/WHEEL
anvil_uplink-0.6.0.dist-info/top_level.txt
anvil_uplink-0.6.0.dist-info/RECORD
